{
  "xsappname": "HiMTA",
  "tenant-mode": "dedicated",
  "description": "Security profile of called application",
  "scopes": [
    {
      "name": "uaa.user",
      "description": "UAA"
    },
    {
      "name": "$XSAPPNAME.view",
      "description": "Display users"
    },
    {
      "name": "$XSAPPNAME.create",
      "description": "Create users"
    }
  ],
  "attributes": [
    {
      "name": "client",
      "description": "Session Client",
      "valueType": "int"
    }
  ],
  "role-templates": [
    {
      "name": "Token_Exchange",
      "description": "UAA",
      "scope-references": [
        "uaa.user"
      ]
    },
    {
      "name": "Admin",
      "description": "Can do anything",
      "scope-references": [
        "$XSAPPNAME.view",
        "$XSAPPNAME.create"
      ],
      "attribute-references": [
      ]
    },
    {
      "name": "SimpleUser",
      "description": "Display mode only",
      "scope-references": [
        "$XSAPPNAME.view"
      ],
      "attribute-references": [
      ]
    }
	  ]
}